<annotation>
	<folder>Mask</folder>
	<filename>with_mask_3121.jpg</filename>
	<path>E:\DataScience\Tensorflow_Object_detection\RealTimeObjectDetection\Tensorflow\workspace\images\data\Mask\with_mask_3121.jpg</path>
	<source>
		<database>Unknown</database>
	</source>
	<size>
		<width>231</width>
		<height>218</height>
		<depth>3</depth>
	</size>
	<segmented>0</segmented>
	<object>
		<name>Mask</name>
		<pose>Unspecified</pose>
		<truncated>0</truncated>
		<difficult>0</difficult>
		<bndbox>
			<xmin>112</xmin>
			<ymin>88</ymin>
			<xmax>199</xmax>
			<ymax>168</ymax>
		</bndbox>
	</object>
</annotation>
